{
  "title": "Another Exmaple",
  "subtitle": "understanding something else",
  "author": {
    "name": "Nick Briz",
    "preferred": "Nick",
    "url": "http://nickbriz.com"
  },
  "description": "Lorem ipsum dolor sit amet, consectetur adipisicing elit, sed do eiusmod tempor incididunt ut labore et dolore magna aliqua. Ut enim ad minim veniam, quis nostrud exercitation ullamco laboris nisi ut aliquip ex ea commodo consequat. Duis aute irure dolor in reprehenderit in voluptate velit esse cillum dolore eu fugiat nulla pariatur. Excepteur sint occaecat cupidatat non proident, sunt in culpa qui officia deserunt mollit anim id est laborum.",
  "keywords": ["art", "example", "css"],
  "main": "main.js",
  "checkpoints": {
    "not the only markup language": 0,
    "artist markup languages": 2
  },
  "references": [
    {
      "note": "'Murray, Janet H.\"Inventing the Medium\" The New Media Reader. Ed. Noah Wardrip-Fruin & Nick Montfort. MIT Press, 2003.",
      "url": "http://www.newmediareader.com/book_samples/nmr-intro-murray-excerpt.pdf"
    },
    {
      "note": "Kay, Alan & Adele Goldberg. \"Personal Dynamic Computer\" Computer 10(3):31-41. March 1977",
      "url": "http://www.newmediareader.com/book_samples/nmr-26-kay.pdf"
    }
  ]
}
